frontera/__init__.py
frontera/exceptions.py
frontera/contrib/__init__.py
frontera/contrib/backends/__init__.py
frontera/contrib/backends/hbase.py
frontera/contrib/backends/partitioners.py
frontera/contrib/backends/memory/__init__.py
frontera/contrib/backends/remote/__init__.py
frontera/contrib/backends/remote/messagebus.py
frontera/contrib/backends/remote/codecs/__init__.py
frontera/contrib/backends/remote/codecs/json.py
frontera/contrib/backends/remote/codecs/msgpack.py
frontera/contrib/backends/sqlalchemy/__init__.py
frontera/contrib/backends/sqlalchemy/components.py
frontera/contrib/backends/sqlalchemy/models.py
frontera/contrib/backends/sqlalchemy/revisiting.py
frontera/contrib/canonicalsolvers/__init__.py
frontera/contrib/canonicalsolvers/basic.py
frontera/contrib/canonicalsolvers/common.py
frontera/contrib/messagebus/__init__.py
frontera/contrib/messagebus/kafkabus.py
frontera/contrib/messagebus/kafka/__init__.py
frontera/contrib/messagebus/kafka/async_.py
frontera/contrib/messagebus/zeromq/__init__.py
frontera/contrib/messagebus/zeromq/broker.py
frontera/contrib/messagebus/zeromq/socket_config.py
frontera/contrib/middlewares/__init__.py
frontera/contrib/middlewares/domain.py
frontera/contrib/middlewares/fingerprint.py
frontera/contrib/requests/__init__.py
frontera/contrib/requests/converters.py
frontera/contrib/requests/manager.py
frontera/contrib/scrapy/__init__.py
frontera/contrib/scrapy/converters.py
frontera/contrib/scrapy/manager.py
frontera/contrib/scrapy/overusedbuffer.py
frontera/contrib/scrapy/settings_adapter.py
frontera/contrib/scrapy/middlewares/__init__.py
frontera/contrib/scrapy/middlewares/schedulers.py
frontera/contrib/scrapy/middlewares/seeds/__init__.py
frontera/contrib/scrapy/middlewares/seeds/file.py
frontera/contrib/scrapy/middlewares/seeds/s3.py
frontera/contrib/scrapy/schedulers/__init__.py
frontera/contrib/scrapy/schedulers/frontier.py
frontera/contrib/scrapy/schedulers/recording.py
frontera/core/__init__.py
frontera/core/codec.py
frontera-0.7.2.dist-info/licenses/AUTHORS
frontera-0.7.2.dist-info/licenses/LICENSE
frontera-0.7.2.dist-info/METADATA
frontera-0.7.2.dist-info/WHEEL
frontera-0.7.2.dist-info/top_level.txt
frontera-0.7.2.dist-info/RECORD
