Metadata-Version: 2.4
Name: frontera
Version: 0.7.2
Summary: A scalable frontier for web crawlers
Home-page: https://github.com/scrapinghub/frontera
Author: Frontera developers
Maintainer: Alexander Sibiryakov
Maintainer-email: sibiryakov@scrapinghub.com
License: BSD
Keywords: crawler,frontier,scrapy,web,requests,frontera
Classifier: Development Status :: 4 - Beta
Classifier: Environment :: Console
Classifier: Intended Audience :: Developers
Classifier: License :: OSI Approved :: BSD License
Classifier: Operating System :: OS Independent
Classifier: Programming Language :: Python
Classifier: Programming Language :: Python :: 3
Classifier: Programming Language :: Python :: 3.9
Classifier: Programming Language :: Python :: 3.10
Classifier: Programming Language :: Python :: 3.11
Classifier: Programming Language :: Python :: 3.12
Classifier: Programming Language :: Python :: 3.13
Classifier: Topic :: Internet :: WWW/HTTP
Classifier: Topic :: Software Development :: Libraries :: Application Frameworks
Classifier: Topic :: Software Development :: Libraries :: Python Modules
Requires-Python: >=3.9
License-File: LICENSE
License-File: AUTHORS
Requires-Dist: w3lib>=1.17.0
Provides-Extra: s3
Requires-Dist: boto>=2.49.0; extra == "s3"
Provides-Extra: scrapy
Requires-Dist: scrapy>=2.7.0; extra == "scrapy"
Provides-Extra: sql
Requires-Dist: cachetools>=0.4.0; extra == "sql"
Requires-Dist: SQLAlchemy<1.4,>=1.0.0; extra == "sql"
Provides-Extra: graphs
Requires-Dist: pyparsing==1.5.7; extra == "graphs"
Requires-Dist: pydot==1.0.28; extra == "graphs"
Requires-Dist: SQLAlchemy; extra == "graphs"
Provides-Extra: logging
Requires-Dist: colorlog>=2.4.0; extra == "logging"
Requires-Dist: python-json-logger>=0.1.5; extra == "logging"
Provides-Extra: tldextract
Requires-Dist: tldextract>=1.5.1; extra == "tldextract"
Provides-Extra: hbase
Requires-Dist: cachetools>=0.4.0; extra == "hbase"
Requires-Dist: happybase>=1.2.0; extra == "hbase"
Requires-Dist: msgpack-python>=0.4; extra == "hbase"
Requires-Dist: setuptools>=50.3.1; extra == "hbase"
Provides-Extra: zeromq
Requires-Dist: pyzmq>=19.0.2; extra == "zeromq"
Requires-Dist: msgpack-python>=0.4; extra == "zeromq"
Provides-Extra: kafka
Requires-Dist: kafka-python<2.1,>=1.4.3; extra == "kafka"
Requires-Dist: twisted>=20.3.0; extra == "kafka"
Provides-Extra: distributed
Requires-Dist: Twisted; extra == "distributed"
Dynamic: author
Dynamic: classifier
Dynamic: home-page
Dynamic: keywords
Dynamic: license
Dynamic: license-file
Dynamic: maintainer
Dynamic: maintainer-email
Dynamic: provides-extra
Dynamic: requires-dist
Dynamic: requires-python
Dynamic: summary
